pytket/extensions/cutensornet/__init__.py
pytket/extensions/cutensornet/_metadata.py
pytket/extensions/cutensornet/general.py
pytket/extensions/cutensornet/py.typed
pytket/extensions/cutensornet/backends/__init__.py
pytket/extensions/cutensornet/backends/cutensornet_backend.py
pytket/extensions/cutensornet/general_state/__init__.py
pytket/extensions/cutensornet/general_state/tensor_network_convert.py
pytket/extensions/cutensornet/general_state/tensor_network_state.py
pytket/extensions/cutensornet/general_state/utils.py
pytket/extensions/cutensornet/structured_state/__init__.py
pytket/extensions/cutensornet/structured_state/classical.py
pytket/extensions/cutensornet/structured_state/general.py
pytket/extensions/cutensornet/structured_state/mps.py
pytket/extensions/cutensornet/structured_state/mps_gate.py
pytket/extensions/cutensornet/structured_state/mps_mpo.py
pytket/extensions/cutensornet/structured_state/simulation.py
pytket/extensions/cutensornet/structured_state/ttn.py
pytket/extensions/cutensornet/structured_state/ttn_gate.py
pytket_cutensornet-0.12.1.dist-info/licenses/LICENSE
pytket_cutensornet-0.12.1.dist-info/METADATA
pytket_cutensornet-0.12.1.dist-info/WHEEL
pytket_cutensornet-0.12.1.dist-info/top_level.txt
pytket_cutensornet-0.12.1.dist-info/RECORD
