Metadata-Version: 2.4
Name: pytket-cutensornet
Version: 0.12.1
Summary: Extension for pytket, providing access to the cuTensorNet Python API.
Author: TKET development team
Author-email: tket-support@quantinuum.com
License: Apache 2
Project-URL: Documentation, https://docs.quantinuum.com/tket/extensions/pytket-cutensornet
Project-URL: Source, https://github.com/CQCL/pytket-cutensornet
Project-URL: Tracker, https://github.com/CQCL/pytket-cutensornet/issues
Classifier: Environment :: Console
Classifier: Programming Language :: Python :: 3.10
Classifier: Programming Language :: Python :: 3.11
Classifier: Programming Language :: Python :: 3.12
Classifier: License :: OSI Approved :: Apache Software License
Classifier: Operating System :: POSIX :: Linux
Classifier: Intended Audience :: Developers
Classifier: Intended Audience :: Science/Research
Classifier: Topic :: Scientific/Engineering
Requires-Python: >=3.10
License-File: LICENSE
Requires-Dist: pytket>=2.11.0
Requires-Dist: networkx>=2.8.8
Dynamic: author
Dynamic: author-email
Dynamic: classifier
Dynamic: description
Dynamic: description-content-type
Dynamic: license
Dynamic: license-file
Dynamic: project-url
Dynamic: requires-dist
Dynamic: requires-python
Dynamic: summary
